setup.py
odoo/addons/hr_assistance_somconnexio/CHANGELOG.md
odoo/addons/hr_assistance_somconnexio/README.rst
odoo/addons/hr_assistance_somconnexio/__init__.py
odoo/addons/hr_assistance_somconnexio/__manifest__.py
odoo/addons/hr_assistance_somconnexio/data/hr_attendance_place.xml
odoo/addons/hr_assistance_somconnexio/data/ir_config_parameter.xml
odoo/addons/hr_assistance_somconnexio/i18n/ca_ES.po
odoo/addons/hr_assistance_somconnexio/i18n/es.po
odoo/addons/hr_assistance_somconnexio/models/__init__.py
odoo/addons/hr_assistance_somconnexio/models/hr_attendance.py
odoo/addons/hr_assistance_somconnexio/models/hr_attendance_place.py
odoo/addons/hr_assistance_somconnexio/models/hr_employee.py
odoo/addons/hr_assistance_somconnexio/models/hr_leave.py
odoo/addons/hr_assistance_somconnexio/security/ir.model.access.csv
odoo/addons/hr_assistance_somconnexio/static/src/css/holidays_highlighter.css
odoo/addons/hr_assistance_somconnexio/static/src/js/holidays_highlighter_model.js
odoo/addons/hr_assistance_somconnexio/static/src/js/holidays_highlighter_renderer.js
odoo/addons/hr_assistance_somconnexio/static/src/js/holidays_highlighter_view.js
odoo/addons/hr_assistance_somconnexio/static/src/js/my_attendances.js
odoo/addons/hr_assistance_somconnexio/static/src/xml/attendance.xml
odoo/addons/hr_assistance_somconnexio/tests/__init__.py
odoo/addons/hr_assistance_somconnexio/tests/models/__init__.py
odoo/addons/hr_assistance_somconnexio/tests/models/test_hr_attendance_process.py
odoo/addons/hr_assistance_somconnexio/views/calendar_view.xml
odoo/addons/hr_assistance_somconnexio/views/hr_attendance.xml
odoo/addons/hr_assistance_somconnexio/views/menus.xml
odoo_addon_hr_assistance_somconnexio.egg-info/PKG-INFO
odoo_addon_hr_assistance_somconnexio.egg-info/SOURCES.txt
odoo_addon_hr_assistance_somconnexio.egg-info/dependency_links.txt
odoo_addon_hr_assistance_somconnexio.egg-info/not-zip-safe
odoo_addon_hr_assistance_somconnexio.egg-info/requires.txt
odoo_addon_hr_assistance_somconnexio.egg-info/top_level.txt