Metadata-Version: 2.4
Name: odoo-addon-hr_assistance_somconnexio
Version: 16.0.1.0.2
Summary: Manage human resources processes in Som Connexió.
Home-page: https://git.coopdevs.org/coopdevs/som-connexio/odoo/odoo-somconnexio
Author: Som Connexió SCCL, Coopdevs Treball SCCL
License: AGPL-3
Classifier: Programming Language :: Python
Classifier: Framework :: Odoo
Classifier: Framework :: Odoo :: 16.0
Classifier: License :: OSI Approved :: GNU Affero General Public License v3
Requires-Python: >=3.10
Requires-Dist: odoo-addon-hr_attendance_report_theoretical_time<16.1dev,>=16.0dev
Requires-Dist: odoo-addon-hr_holidays_leave_auto_approve<16.1dev,>=16.0dev
Requires-Dist: odoo-addon-hr_holidays_public<16.1dev,>=16.0dev
Requires-Dist: odoo-addon-somconnexio<16.1dev,>=16.0dev
Requires-Dist: odoo<16.1dev,>=16.0a
Dynamic: author
Dynamic: classifier
Dynamic: description
Dynamic: home-page
Dynamic: license
Dynamic: requires-dist
Dynamic: requires-python
Dynamic: summary
